ld_data/__init__.py
ld_data-0.0.1.dist-info/WHEEL
ld_data-0.0.1.dist-info/METADATA
ld_data-0.0.1.dist-info/RECORD
